AUTHORS.rst
CONTRIBUTING.rst
HISTORY.rst
LICENSE
MANIFEST.in
README.rst
setup.cfg
setup.py
docs/Makefile
docs/authors.rst
docs/conf.py
docs/contributing.rst
docs/global_search.rst
docs/history.rst
docs/index.rst
docs/installation.rst
docs/introduction.rst
docs/local_search.rst
docs/make.bat
docs/_build/html/_static/ajax-loader.gif
docs/_build/html/_static/comment-bright.png
docs/_build/html/_static/comment-close.png
docs/_build/html/_static/comment.png
docs/_build/html/_static/down-pressed.png
docs/_build/html/_static/down.png
docs/_build/html/_static/file.png
docs/_build/html/_static/minus.png
docs/_build/html/_static/plus.png
docs/_build/html/_static/up-pressed.png
docs/_build/html/_static/up.png
pott/__init__.py
pott/cli.py
pott/index.py
pott/option.py
pott/paper.py
pott/screen.py
pott/yaml.py
pott.egg-info/PKG-INFO
pott.egg-info/SOURCES.txt
pott.egg-info/dependency_links.txt
pott.egg-info/entry_points.txt
pott.egg-info/not-zip-safe
pott.egg-info/requires.txt
pott.egg-info/top_level.txt
pott/assistants/__init__.py
pott/assistants/assistant.py
pott/assistants/global_assistant.py
pott/assistants/local_assistant.py
pott/files/__init__.py
pott/files/file.py
pott/files/pdf.py
pott/files/text.py
pott/utils/__init__.py
pott/utils/html_utils.py
pott/utils/log.py
tests/__init__.py
tests/test.pdf
tests/test_assistant.py
tests/test_cli.py
tests/test_html_utils.py
tests/test_index.py
tests/test_local_assistant.py
tests/test_option.py
tests/test_pdf.py
tests/test_yaml.py