Metadata-Version: 1.1
Name: pott
Version: 0.0.1
Summary: paper organization tool on terminal
Home-page: https://github.com/jun-harashima/pott
Author: Jun Harashima
Author-email: j.harashima@gmail.com
License: MIT license
Keywords: pott
Platform: UNKNOWN
Classifier: Development Status :: 2 - Pre-Alpha
Classifier: Intended Audience :: Developers
Classifier: License :: OSI Approved :: MIT License
Classifier: Natural Language :: English
Classifier: Programming Language :: Python :: 2
Classifier: Programming Language :: Python :: 2.7
Classifier: Programming Language :: Python :: 3
Classifier: Programming Language :: Python :: 3.4
Classifier: Programming Language :: Python :: 3.5
Classifier: Programming Language :: Python :: 3.6
